LICENSE
MANIFEST.in
README.md
setup.py
django_fusionbox_blog.egg-info/PKG-INFO
django_fusionbox_blog.egg-info/SOURCES.txt
django_fusionbox_blog.egg-info/dependency_links.txt
django_fusionbox_blog.egg-info/namespace_packages.txt
django_fusionbox_blog.egg-info/requires.txt
django_fusionbox_blog.egg-info/top_level.txt
fusionbox/__init__.py
fusionbox/blog/__init__.py
fusionbox/blog/admin.py
fusionbox/blog/feeds.py
fusionbox/blog/models.py
fusionbox/blog/tests.py
fusionbox/blog/urls.py
fusionbox/blog/views.py
fusionbox/blog/management/__init__.py
fusionbox/blog/management/commands/__init__.py
fusionbox/blog/management/commands/seed_blogs.py
fusionbox/blog/migrations/0001_initial.py
fusionbox/blog/migrations/0002_auto__add_field_blog_summary__chg_field_blog_tags.py
fusionbox/blog/migrations/__init__.py