Metadata-Version: 1.1
Name: django-fusionbox-blog
Version: 1.0.2
Summary: 
